README.md
setup.py
SqliInjection/main.py
SqliInjection.egg-info/PKG-INFO
SqliInjection.egg-info/SOURCES.txt
SqliInjection.egg-info/dependency_links.txt
SqliInjection.egg-info/entry_points.txt
SqliInjection.egg-info/requires.txt
SqliInjection.egg-info/top_level.txt
SqliInjection/includes/__init__.py
SqliInjection/includes/bot.py
SqliInjection/includes/file.py
SqliInjection/includes/scan.py
SqliInjection/includes/write.py
SqliInjection/units/__init__.py
SqliInjection/units/banner.py
SqliInjection/units/checknet.py
SqliInjection/units/url.py