Metadata-Version: 2.1
Name: SqliInjection
Version: 1.0
Author: @Umasankar
Author-email: <sankar3102004@gmail.com>
Classifier: Programming Language :: Python :: 3
Classifier: Operating System :: Unix
Classifier: Operating System :: MacOS :: MacOS X
Classifier: Operating System :: Microsoft :: Windows
Requires-Dist: argparse
Requires-Dist: requests
